{
  "id": "25142dd8933a4e89aa9ece5188174d63",
  "title": "Their Secrets",
  "description": "You receive an invitation to the funeral of your high school friend Xu Dongming, murdered on his thirtieth birthday. His killer, Daniel, another friend, left a keepsake that transports you back to Princeton International Academy, revealing their tragic origins.",
  "keyImages": [
    {
      "type": "DieselGameBox",
      "url": "https://cdn1.epicgames.com/spt-assets/c10cdd7a991443359a7f029bb18ac674/their-secrets-62hth.jpg",
      "md5": "8c4ec3ea2e1a04c943b5811b346d189b",
      "width": 2560,
      "height": 1440,
      "size": 461184,
      "uploadedDate": "2024-09-13T02:40:49.965Z",
      "alt": "Their Secrets Offer"
    },
    {
      "type": "DieselGameBoxTall",
      "url": "https://cdn1.epicgames.com/spt-assets/c10cdd7a991443359a7f029bb18ac674/their-secrets-ro5e5.jpg",
      "md5": "523aa60fa0580be386a3b4ecb8dfb27b",
      "width": 1200,
      "height": 1600,
      "size": 406740,
      "uploadedDate": "2024-09-13T02:40:48.999Z",
      "alt": "Download Their Secrets Offer"
    }
  ],
  "categories": [
    {
      "path": "games"
    },
    {
      "path": "applications"
    }
  ],
  "namespace": "5cc55bc3565c4c6299971b5a95d9d448",
  "status": "ACTIVE",
  "creationDate": "2024-09-09T07:39:08.347Z",
  "lastModifiedDate": "2024-09-20T02:45:31.327Z",
  "customAttributes": {
    "FolderName": {
      "type": "STRING",
      "value": "TheirSecretsJ1Eis"
    }
  },
  "entitlementName": "25142dd8933a4e89aa9ece5188174d63",
  "entitlementType": "EXECUTABLE",
  "itemType": "DURABLE",
  "releaseInfo": [
    {
      "id": "116cd4d3d59447f6bc1a6c9daa89bdb0",
      "appId": "b5ec34f69e314e6fba66125044c4d8de",
      "platform": [
        "Windows"
      ]
    }
  ],
  "developer": "BING WORLD TECHNOLOGY MEDIA LIMITED",
  "developerId": "o-er2m8xv5fa9p833rqwm4pa6bc7v5nh",
  "endOfSupport": false,
  "applicationId": "fghi4567daQZwxqkYXaT41vFOEc4WQZ2",
  "requiresSecureAccount": false,
  "unsearchable": false
}