{
  "id": "4bed145cb2024257be0b99a5fcd16d9a",
  "title": "Medieval Weapons and Armor Inventory Sounds Bundle",
  "description": "Give life to your inventory related actions with our affordable Medieval Weapons and Armor Inventory Sounds Bundle!",
  "longDescription": "<p>Introducing our Medieval Weapons and Armor Bundle, a comprehensive collection crafted for immersive gameplay experiences. </p><p><br /></p><ul><li><a href=\"https://www.unrealengine.com/marketplace/en-US/product/8e7ba15014d54731b3c239f8e8dd2c9d\" rel=\"nofollow\"><strong>Medieval Weapons Inventory Sound Pack:</strong></a> Dive into the world of medieval warfare with meticulously recorded sounds of essential weapons and crafting actions.</li></ul><p><a href=\"https://soundcloud.com/cyberwave-orchestra/sets/medieval-weapons-inventory-sounds?si&#61;ba6019c1c68e4540a21800e2934ccb8c&amp;utm_source&#61;clipboard&amp;utm_medium&#61;text&amp;utm_campaign&#61;social_sharing\" rel=\"nofollow\">SoundCloud Preview</a></p><p><a href=\"https://drive.google.com/file/d/1XK2GezzHdk-9aOIQTFM_tdJUmNNnU-EX/view?usp&#61;sharing\" rel=\"nofollow\">Files Included List</a></p><p><br /></p><ul><li><a href=\"https://www.unrealengine.com/marketplace/en-US/product/ae04745e0cb446d0b5dca626a12ed7b1\" rel=\"nofollow\"><strong>Medieval Fantasy Armor SFX Pack:</strong> </a>Equip your heroes with authentic sounds of plate, cloth, leather, and chainmail armor, enhancing the immersive experience of your game.</li></ul><p><a href=\"https://soundcloud.com/cyberwave-orchestra/sets/medieval-fantasy-armor-sfx-pick-up-equip-and-other-inventory-sounds?si&#61;bd61743d40e3487c85a790c41491eded&amp;utm_source&#61;clipboard&amp;utm_medium&#61;text&amp;utm_campaign&#61;social_sharing\" rel=\"nofollow\">SoundCloud Preview</a></p><p><a href=\"https://drive.google.com/file/d/108AfkkybRu0pn3VmE4msO5oxSBkCOiqD/view?usp&#61;sharing\" rel=\"nofollow\">All Files List</a></p><p><br /></p><p>Combine the power of both packs to transport players to the heart of medieval battlefields, complete with rich weapon inventories and realistic armor effects.</p><p><br /></p><p><br /></p><p><br /></p><p><em>We appreciate hearing from our buyers and value your feedback! Leaving a review, providing suggestions, or reaching out to us directly helps us understand your needs and preferences better. As authors, we genuinely enjoy interacting with the developers who use our product. </em></p><p><br /></p><p><em>Thank you,</em></p><p><em>Cyberwave Orchestra</em></p><p><em>cyberwaveorchestra&#64;gmail.com</em></p><p><br /></p>",
  "technicalDetails": "<p>Number of Audio Wavs: 224</p><p>Number of Audio Cues: 224</p><p>Sample rate/bit rate: 16bit 44.100 Wav.</p><p>Does music loop: No</p><p>Minutes of audio provided: 05 min, 09 sec</p><p>Supported Development Platforms: All</p><p><br /></p>",
  "keyImages": [
    {
      "type": "Screenshot",
      "url": "https://cdn1.epicgames.com/ue/product/Screenshot/WeaponsArmor Bundle Unreal Main-1920x1080-b29280fb0573da040f2a785f8dc9d9cb.jpg",
      "md5": "b29280fb0573da040f2a785f8dc9d9cb",
      "width": 1920,
      "height": 1080,
      "size": 1203652,
      "uploadedDate": "2024-05-02T13:22:42.314Z"
    },
    {
      "type": "Thumbnail",
      "url": "https://cdn1.epicgames.com/ue/product/Thumbnail/MedievalWeaponsandArmorInventorySoundsBundle_thumb-284x284-6677c18ee425c02c0e566501d9a8240a.png",
      "md5": "6677c18ee425c02c0e566501d9a8240a",
      "width": 284,
      "height": 284,
      "size": 177551,
      "uploadedDate": "2024-05-02T13:22:42.741Z"
    },
    {
      "type": "Featured",
      "url": "https://cdn1.epicgames.com/ue/product/Featured/MedievalWeaponsandArmorInventorySoundsBundle_featured-894x488-061e749a7b2a2608be111329e0290f10.png",
      "md5": "061e749a7b2a2608be111329e0290f10",
      "width": 894,
      "height": 488,
      "size": 738166,
      "uploadedDate": "2024-05-02T13:22:42.942Z"
    },
    {
      "type": "Snapshot",
      "url": "https://cdn1.epicgames.com/ue/product/Snapshot/WeaponsArmor Bundle Unreal Main-1920x1080-b29280fb0573da040f2a785f8dc9d9cb_Snapshot.jpg",
      "md5": "460864e71550d0fee0a5a10741d7fb07",
      "width": 150,
      "height": 74,
      "size": 6970,
      "uploadedDate": "2024-05-02T13:22:42.594Z"
    }
  ],
  "categories": [
    {
      "path": "assets"
    },
    {
      "path": "assets/soundfx"
    }
  ],
  "namespace": "ue",
  "status": "ACTIVE",
  "creationDate": "2024-05-04T05:17:47.566Z",
  "lastModifiedDate": "2024-12-29T14:26:25.083Z",
  "customAttributes": {},
  "entitlementName": "4bed145cb2024257be0b99a5fcd16d9a",
  "entitlementType": "EXECUTABLE",
  "itemType": "DURABLE",
  "releaseInfo": [
    {
      "id": "7e0aa680ae0e4cd38262bcc509fdf919",
      "appId": "Medieval4bed145cb202V1",
      "compatibleApps": [
        "UE_4.23",
        "UE_4.24",
        "UE_4.25",
        "UE_4.26",
        "UE_4.27",
        "UE_5.0",
        "UE_5.1",
        "UE_5.2",
        "UE_5.3",
        "UE_5.4"
      ],
      "platform": [
        "Android",
        "Gear VR",
        "HoloLens 2",
        "HTML5",
        "iOS",
        "Linux",
        "Mac",
        "Nintendo Switch",
        "Oculus",
        "PS4",
        "SteamVR / HTC Vive",
        "Win32",
        "Windows",
        "Xbox One"
      ],
      "dateAdded": "2024-05-02T00:00:00.000Z",
      "releaseNote": "",
      "versionTitle": "WeaponsArmorInventory 1.0"
    }
  ],
  "developer": "Cyberwave Orchestra",
  "developerId": "o-lnx9gxrgtdlpf7kuvbxgpx23b9celz",
  "endOfSupport": false,
  "requiresSecureAccount": false,
  "unsearchable": false
}