{
  "id": "53fd671e653a46dd870fa7f9425a476d",
  "title": "Points AI Wave System",
  "description": "Points AI Wave System. Template System for tower defense projects.",
  "longDescription": "<p>The system is designed for wave projects such as tower defense. You can quickly create a tower defense using this asset.</p><p>To work with it, you just need to add a few blueprints to the scene and fill in the fields.</p><p>The logic of movement is already inside the asset, you do not need to create your own.</p><p><br /></p><p><strong>Update 1.1</strong></p><ul><li>Added a Health component. Ragdoll inside. Now you can set the health of units when spawning.</li><li>Added damage size to the tower examples.</li><li>Documentation updated.</li></ul><p><br /></p><p><a href=\"https://youtu.be/VkXPBH0VIvo\" rel=\"nofollow\"><strong>Preview</strong></a></p><p><br /></p><p><a href=\"https://drive.google.com/file/d/1cmssASIVRAsab3JqeirdKmsPT4UzRVlq/view?usp&#61;sharing\" rel=\"nofollow\"><strong>Documentation</strong></a></p><p><br /></p><p><a href=\"https://www.unrealengine.com/marketplace/en-US/profile/ProMaxx&#43;Studio&#43;-&#43;Characters?count&#61;20&amp;sortBy&#61;effectiveDate&amp;sortDir&#61;DESC&amp;start&#61;0\" rel=\"nofollow\"><strong>ProMaxx Studio Characters</strong></a></p>",
  "technicalDetails": "<p>Features:</p><ul><li>The ability to use an unlimited number of wave spawners to build more complex levels.</li><li>You can choose unique paths for each spawner.</li><li>Customizable win, loss, completing a wave events</li><li>Two AI modes: Air or Land</li><li>Mixed waves, selective delayed spawn</li><li>Tower blanks with three types of attacks (Laser FX, Laser shot (projectile), Missile)</li><li>Built-in logic of winning, losing</li><li>Easy to add and use</li><li>Health Component</li><li>Damage</li><li>Network Replicated</li></ul><p><br /></p><p>If you liked the asset, please feel free to leave a review.</p><p><br /></p><p>Number of Blueprints: 8</p><p>Input: Keyboard, Mouse</p><p>Network Replicated: Yes</p>",
  "keyImages": [
    {
      "type": "Screenshot",
      "url": "https://cdn1.epicgames.com/ue/product/Screenshot/Logo2-1920x1080-cfe3b7e848e7590dffa1984d50a63b6d.png",
      "md5": "cfe3b7e848e7590dffa1984d50a63b6d",
      "width": 1920,
      "height": 1080,
      "size": 2179125,
      "uploadedDate": "2023-11-27T15:38:58.882Z"
    },
    {
      "type": "Screenshot",
      "url": "https://cdn1.epicgames.com/ue/product/Screenshot/2-1920x1080-a74d972ab32cda14f2e0da9df668d62d.jpg",
      "md5": "a74d972ab32cda14f2e0da9df668d62d",
      "width": 1920,
      "height": 1080,
      "size": 1322427,
      "uploadedDate": "2023-01-23T20:21:34.880Z"
    },
    {
      "type": "Screenshot",
      "url": "https://cdn1.epicgames.com/ue/product/Screenshot/3-1920x1080-f05516191b50fa7b1bdd579e805fd65d.jpg",
      "md5": "f05516191b50fa7b1bdd579e805fd65d",
      "width": 1920,
      "height": 1080,
      "size": 1041015,
      "uploadedDate": "2023-01-23T20:21:35.417Z"
    },
    {
      "type": "Screenshot",
      "url": "https://cdn1.epicgames.com/ue/product/Screenshot/4-1920x1080-18041ea9f53a12af92fe30029e080213.jpg",
      "md5": "18041ea9f53a12af92fe30029e080213",
      "width": 1920,
      "height": 1080,
      "size": 698309,
      "uploadedDate": "2023-01-23T20:21:35.895Z"
    },
    {
      "type": "Screenshot",
      "url": "https://cdn1.epicgames.com/ue/product/Screenshot/5-1920x1080-a64a967d9c688fc6ed30e95c86c361de.jpg",
      "md5": "a64a967d9c688fc6ed30e95c86c361de",
      "width": 1920,
      "height": 1080,
      "size": 1198600,
      "uploadedDate": "2023-01-23T20:21:36.307Z"
    },
    {
      "type": "Thumbnail",
      "url": "https://cdn1.epicgames.com/ue/product/Thumbnail/PointsAIWaveSystem_thumb-284x284-b2b5db85b1b3d8a1c251f0c4d91643dd.png",
      "md5": "b2b5db85b1b3d8a1c251f0c4d91643dd",
      "width": 284,
      "height": 284,
      "size": 103733,
      "uploadedDate": "2023-11-27T15:38:59.366Z"
    },
    {
      "type": "Featured",
      "url": "https://cdn1.epicgames.com/ue/product/Featured/PointsAIWaveSystem_featured-894x488-b79042edba70f1a078eff6bb23fbec8a.png",
      "md5": "b79042edba70f1a078eff6bb23fbec8a",
      "width": 894,
      "height": 488,
      "size": 578939,
      "uploadedDate": "2023-11-27T15:38:59.530Z"
    },
    {
      "type": "Snapshot",
      "url": "https://cdn1.epicgames.com/ue/product/Snapshot/Logo2-1920x1080-cfe3b7e848e7590dffa1984d50a63b6d_Snapshot.png",
      "md5": "e4af41d416d1da9125dd89a379317122",
      "width": 150,
      "height": 74,
      "size": 8498,
      "uploadedDate": "2023-11-27T15:38:59.320Z"
    },
    {
      "type": "Snapshot",
      "url": "https://cdn1.epicgames.com/ue/product/Snapshot/11-1920x1080-d7f84ccc314647afe06b1d420d3a8981_Snapshot.png",
      "md5": "2d062295b296a771219b5fc608c0cf3e",
      "width": 150,
      "height": 74,
      "size": 7960,
      "uploadedDate": "2023-01-23T20:21:34.682Z"
    },
    {
      "type": "Snapshot",
      "url": "https://cdn1.epicgames.com/ue/product/Snapshot/2-1920x1080-a74d972ab32cda14f2e0da9df668d62d_Snapshot.jpg",
      "md5": "eb0baf68033878dd2bc523c2da15b4d1",
      "width": 150,
      "height": 74,
      "size": 6931,
      "uploadedDate": "2023-01-23T20:21:35.193Z"
    },
    {
      "type": "Snapshot",
      "url": "https://cdn1.epicgames.com/ue/product/Snapshot/3-1920x1080-f05516191b50fa7b1bdd579e805fd65d_Snapshot.jpg",
      "md5": "1377fa0e6ca8d7525503a99352641fdb",
      "width": 150,
      "height": 74,
      "size": 5358,
      "uploadedDate": "2023-01-23T20:21:35.676Z"
    },
    {
      "type": "Snapshot",
      "url": "https://cdn1.epicgames.com/ue/product/Snapshot/4-1920x1080-18041ea9f53a12af92fe30029e080213_Snapshot.jpg",
      "md5": "027d99dbc4a9708d0c075b65c157b7bf",
      "width": 150,
      "height": 74,
      "size": 4960,
      "uploadedDate": "2023-01-23T20:21:36.138Z"
    },
    {
      "type": "Snapshot",
      "url": "https://cdn1.epicgames.com/ue/product/Snapshot/5-1920x1080-a64a967d9c688fc6ed30e95c86c361de_Snapshot.jpg",
      "md5": "ca594ab1160c0166b35d4d8868996553",
      "width": 150,
      "height": 74,
      "size": 7466,
      "uploadedDate": "2023-01-23T20:21:36.565Z"
    }
  ],
  "categories": [
    {
      "path": "assets/blueprints"
    },
    {
      "path": "assets"
    }
  ],
  "namespace": "ue",
  "status": "ACTIVE",
  "creationDate": "2023-01-25T18:55:11.808Z",
  "lastModifiedDate": "2024-11-13T14:53:52.253Z",
  "customAttributes": {},
  "entitlementName": "53fd671e653a46dd870fa7f9425a476d",
  "entitlementType": "EXECUTABLE",
  "itemType": "DURABLE",
  "releaseInfo": [
    {
      "id": "077609dd6f584b3dba80f1f7b0384815",
      "appId": "PointsWa53fd671e653aV1",
      "compatibleApps": [
        "UE_4.24",
        "UE_4.25",
        "UE_4.26",
        "UE_4.27",
        "UE_5.0",
        "UE_5.1",
        "UE_5.2",
        "UE_5.3",
        "UE_5.4"
      ],
      "platform": [
        "Linux",
        "Mac",
        "Win32",
        "Windows"
      ],
      "dateAdded": "2023-01-24T00:00:00.000Z",
      "releaseNote": "",
      "versionTitle": "1.0"
    }
  ],
  "developer": "ProMaxx Studio",
  "developerId": "o-f3q639r9bkh4ud7r7ukea4849yjfnk",
  "endOfSupport": false,
  "requiresSecureAccount": false,
  "unsearchable": false
}