{
  "id": "86a1e51d55484ba78af3cf952096c05e",
  "title": "Knight vs Giant: The Broken Excalibur Soundtrack_DigitalExtraAudience",
  "description": "Knight vs Giant: The Broken Excalibur Soundtrack_DigitalExtraAudience",
  "categories": [
    {
      "path": "audience"
    },
    {
      "path": "public"
    }
  ],
  "namespace": "973549a03a1441058badf7a1bc8b565d",
  "status": "ACTIVE",
  "creationDate": "2023-09-27T08:00:03.673Z",
  "lastModifiedDate": "2023-09-27T08:00:04.058Z",
  "entitlementName": "86a1e51d55484ba78af3cf952096c05e",
  "entitlementType": "AUDIENCE",
  "itemType": "DURABLE",
  "developer": "PQube",
  "developerId": "o-9l5q72cwxf99kwzprbq6f558383l2l",
  "endOfSupport": false,
  "requiresSecureAccount": false,
  "unsearchable": false
}