{
  "id": "b2875b903b1c4d9c8094a0be9100ac7d",
  "title": "Security Cameras Pack",
  "description": "Security Cameras Pack",
  "longDescription": "<p>PLEASE NOTE: The DemoScene in 4.27 may be too bright. If it happens, please go to World Outliner, find SkyLight and reset the Intensity Scale value for Skylight in Details.</p><p><br /></p><p>Modern Security Cameras Pack.</p><p>Demo: <a href=\"https://youtu.be/AxaPpTS4m2g\" rel=\"nofollow\">https://youtu.be/AxaPpTS4m2g</a></p><p>How to Use: <a href=\"https://www.youtube.com/watch?v&#61;Fju3KcR_K-c&amp;feature&#61;youtu.be\" rel=\"nofollow\">https://youtu.be/Fju3KcR_K-c</a></p><p>The package contains several most popular types of security cameras:</p><ul><li>Box Style Security Camera</li><li>Dome Security Camera</li><li>PTZ Security Camera</li><li>Bullet Security Camera</li><li>Wireless IP Camera</li><li>Plus two electrical boxes for a pillar.</li></ul>",
  "technicalDetails": "<p>Features:</p><ul><li>30 Optimized Static Meshes</li><li>20 Blueprints</li><li>High-quality 4k textures</li><li>Master Material Setup: Controls for Roughness, Metallic, Base Color Tint (Mask), Normal, Emissive</li><li>Channel packed: Metallic, Roughness, Ambient Occlusion, Tint Mask</li></ul><p><br /></p><p>Number of Unique Meshes: 30</p><p>Collision: Yes. Automatically generated.</p><p>Vertex Count: from 63 to 2377</p><p>LODs: No</p><p>Number of Materials and Material Instances: 27</p><p>Number of Textures: 104</p><p>Texture Resolutions: 4096</p><p>Supported Development Platforms:</p><p>Windows: Yes</p><p>Supported Target Build Platforms: Not tested</p><p><br /></p><p>Support:</p><p>contact&#64;hardsurfacestudio.com</p>",
  "keyImages": [
    {
      "type": "Screenshot",
      "url": "https://cdn1.epicgames.com/ue/product/Screenshot/Security Cameras Pack 01-1920x1080-2af156bcb16a1a63af6c6033b3f6e5a9.jpg",
      "md5": "2af156bcb16a1a63af6c6033b3f6e5a9",
      "width": 1920,
      "height": 1080,
      "size": 1915373,
      "uploadedDate": "2020-06-02T14:11:47.749Z"
    },
    {
      "type": "Screenshot",
      "url": "https://cdn1.epicgames.com/ue/product/Screenshot/Security Cameras Pack 10-1920x1080-ff2af2ddcf9f69c35d37d715f5637111.jpg",
      "md5": "ff2af2ddcf9f69c35d37d715f5637111",
      "width": 1920,
      "height": 1080,
      "size": 828242,
      "uploadedDate": "2020-06-02T14:11:48.270Z"
    },
    {
      "type": "Screenshot",
      "url": "https://cdn1.epicgames.com/ue/product/Screenshot/Security Cameras Pack 04-1920x1080-ab5c6ee88fe33e768393d672a2018df2.jpg",
      "md5": "ab5c6ee88fe33e768393d672a2018df2",
      "width": 1920,
      "height": 1080,
      "size": 956719,
      "uploadedDate": "2020-05-29T12:05:40.446Z"
    },
    {
      "type": "Screenshot",
      "url": "https://cdn1.epicgames.com/ue/product/Screenshot/Security Cameras Pack 05-1920x1080-9d3ff5e8675de749cbad4be81277b223.jpg",
      "md5": "9d3ff5e8675de749cbad4be81277b223",
      "width": 1920,
      "height": 1080,
      "size": 877887,
      "uploadedDate": "2020-05-29T12:05:40.861Z"
    },
    {
      "type": "Screenshot",
      "url": "https://cdn1.epicgames.com/ue/product/Screenshot/Security Cameras Pack 06-1920x1080-1a331185651b7b85887dc132d0b42572.jpg",
      "md5": "1a331185651b7b85887dc132d0b42572",
      "width": 1920,
      "height": 1080,
      "size": 757740,
      "uploadedDate": "2020-05-29T12:05:41.465Z"
    },
    {
      "type": "Screenshot",
      "url": "https://cdn1.epicgames.com/ue/product/Screenshot/Security Cameras Pack 07-1920x1080-177f8e2535aaa3f7df8d571e9dba3304.jpg",
      "md5": "177f8e2535aaa3f7df8d571e9dba3304",
      "width": 1920,
      "height": 1080,
      "size": 1212370,
      "uploadedDate": "2020-05-29T12:05:41.957Z"
    },
    {
      "type": "Screenshot",
      "url": "https://cdn1.epicgames.com/ue/product/Screenshot/Security Cameras Pack 08-1920x1080-fa676bcff0306848b9d6252c0750e017.jpg",
      "md5": "fa676bcff0306848b9d6252c0750e017",
      "width": 1920,
      "height": 1080,
      "size": 969561,
      "uploadedDate": "2020-05-29T12:05:42.439Z"
    },
    {
      "type": "Screenshot",
      "url": "https://cdn1.epicgames.com/ue/product/Screenshot/Security Cameras Pack 09-1920x1080-b1295580286080bdc5d9edabdef7b9a4.jpg",
      "md5": "b1295580286080bdc5d9edabdef7b9a4",
      "width": 1920,
      "height": 1080,
      "size": 1080816,
      "uploadedDate": "2020-05-29T12:05:42.825Z"
    },
    {
      "type": "Thumbnail",
      "url": "https://cdn1.epicgames.com/ue/product/Thumbnail/SecurityCamerasPack_thumb-284x284-b4cdb19635a285d3f58844d7eda09026.png",
      "md5": "b4cdb19635a285d3f58844d7eda09026",
      "width": 284,
      "height": 284,
      "size": 156838,
      "uploadedDate": "2020-05-29T12:05:43.182Z"
    },
    {
      "type": "Featured",
      "url": "https://cdn1.epicgames.com/ue/product/Featured/SecurityCamerasPack_featured-894x488-7ef2b6dc273155773e8b5758adcaafc2.png",
      "md5": "7ef2b6dc273155773e8b5758adcaafc2",
      "width": 894,
      "height": 488,
      "size": 685115,
      "uploadedDate": "2020-05-29T12:05:43.449Z"
    },
    {
      "type": "Snapshot",
      "url": "https://cdn1.epicgames.com/ue/product/Snapshot/Security Cameras Pack 01-1920x1080-2af156bcb16a1a63af6c6033b3f6e5a9_Snapshot.jpg",
      "md5": "702afa1c2c015110bff323554f71caa0",
      "width": 150,
      "height": 74,
      "size": 5439,
      "uploadedDate": "2020-06-02T14:11:48.143Z"
    },
    {
      "type": "Snapshot",
      "url": "https://cdn1.epicgames.com/ue/product/Snapshot/Security Cameras Pack 10-1920x1080-ff2af2ddcf9f69c35d37d715f5637111_Snapshot.jpg",
      "md5": "e95345abb254f213a35eac68247bc26c",
      "width": 150,
      "height": 74,
      "size": 4328,
      "uploadedDate": "2020-06-02T14:11:48.536Z"
    },
    {
      "type": "Snapshot",
      "url": "https://cdn1.epicgames.com/ue/product/Snapshot/Security Cameras Pack 01-1920x1080-f393e11813d9ce61aefe593977d1c0c4_Snapshot.jpg",
      "md5": "843fe42058484c52c27bae97447f33a2",
      "width": 150,
      "height": 74,
      "size": 5743,
      "uploadedDate": "2020-05-29T12:05:39.486Z"
    },
    {
      "type": "Snapshot",
      "url": "https://cdn1.epicgames.com/ue/product/Snapshot/Security Cameras Pack 02-1920x1080-1b0352612b05004f742829e030cfb158_Snapshot.jpg",
      "md5": "942621f076ddb4f5c5be195df9140b66",
      "width": 150,
      "height": 74,
      "size": 4852,
      "uploadedDate": "2020-05-29T12:05:39.862Z"
    },
    {
      "type": "Snapshot",
      "url": "https://cdn1.epicgames.com/ue/product/Snapshot/Security Cameras Pack 03-1920x1080-397763227def4304e1e61e99592a9fee_Snapshot.jpg",
      "md5": "28f400f35fe8dfb4c39b3bf126c1a492",
      "width": 150,
      "height": 74,
      "size": 7314,
      "uploadedDate": "2020-05-29T12:05:40.344Z"
    },
    {
      "type": "Snapshot",
      "url": "https://cdn1.epicgames.com/ue/product/Snapshot/Security Cameras Pack 04-1920x1080-ab5c6ee88fe33e768393d672a2018df2_Snapshot.jpg",
      "md5": "7c173dbd466d73cc4d320044523af537",
      "width": 150,
      "height": 74,
      "size": 7253,
      "uploadedDate": "2020-05-29T12:05:40.720Z"
    },
    {
      "type": "Snapshot",
      "url": "https://cdn1.epicgames.com/ue/product/Snapshot/Security Cameras Pack 05-1920x1080-9d3ff5e8675de749cbad4be81277b223_Snapshot.jpg",
      "md5": "a53325e301556e647e4882013a1fd793",
      "width": 150,
      "height": 74,
      "size": 6676,
      "uploadedDate": "2020-05-29T12:05:41.118Z"
    },
    {
      "type": "Snapshot",
      "url": "https://cdn1.epicgames.com/ue/product/Snapshot/Security Cameras Pack 06-1920x1080-1a331185651b7b85887dc132d0b42572_Snapshot.jpg",
      "md5": "9f9cb202a8e14edcb165c8d38dc8a026",
      "width": 150,
      "height": 74,
      "size": 6141,
      "uploadedDate": "2020-05-29T12:05:41.715Z"
    },
    {
      "type": "Snapshot",
      "url": "https://cdn1.epicgames.com/ue/product/Snapshot/Security Cameras Pack 07-1920x1080-177f8e2535aaa3f7df8d571e9dba3304_Snapshot.jpg",
      "md5": "45e71d9306a0174d7f2d9ba67b430c87",
      "width": 150,
      "height": 74,
      "size": 5596,
      "uploadedDate": "2020-05-29T12:05:42.253Z"
    },
    {
      "type": "Snapshot",
      "url": "https://cdn1.epicgames.com/ue/product/Snapshot/Security Cameras Pack 08-1920x1080-fa676bcff0306848b9d6252c0750e017_Snapshot.jpg",
      "md5": "961759d75edf376ac5821a29bb0302db",
      "width": 150,
      "height": 74,
      "size": 4288,
      "uploadedDate": "2020-05-29T12:05:42.719Z"
    },
    {
      "type": "Snapshot",
      "url": "https://cdn1.epicgames.com/ue/product/Snapshot/Security Cameras Pack 09-1920x1080-b1295580286080bdc5d9edabdef7b9a4_Snapshot.jpg",
      "md5": "9f27e2dcd0290eb68355ea15f0dfe621",
      "width": 150,
      "height": 74,
      "size": 4842,
      "uploadedDate": "2020-05-29T12:05:43.088Z"
    }
  ],
  "categories": [
    {
      "path": "assets/props"
    },
    {
      "path": "assets"
    }
  ],
  "namespace": "ue",
  "status": "SUNSET",
  "creationDate": "2020-06-11T15:53:06.316Z",
  "lastModifiedDate": "2022-02-07T13:41:06.789Z",
  "entitlementName": "b2875b903b1c4d9c8094a0be9100ac7d",
  "entitlementType": "EXECUTABLE",
  "itemType": "DURABLE",
  "releaseInfo": [
    {
      "id": "c9e6ba04f0c64a91ae1e846303f8b3ec",
      "appId": "Securityb2875b903b1cV3",
      "compatibleApps": [
        "UE_4.25",
        "UE_4.26",
        "UE_4.27"
      ],
      "platform": [
        "Windows"
      ],
      "dateAdded": "2020-06-08T00:00:00.000Z",
      "releaseNote": "",
      "versionTitle": "Security Cameras Pack"
    }
  ],
  "developer": "Hard Surface Studio",
  "developerId": "o-3479lxlw7fx3cszuvjuu6uxvlh9cdn",
  "endOfSupport": false,
  "unsearchable": false
}