{
  "id": "b6c08618a4514f0a9f89819e7d8edd50",
  "title": "Sci-Fi World Colony Sound Effects",
  "description": "Create the perfect room tone and sound environment for your next sci-fi game, film, and audio productions. Sci-fi World: Colony is an ambience loop library inspired by the human race of award-winning game “Starcraft”.",
  "longDescription": "<p><a href=\"https://soundcloud.com/epic-sounds-and-fx/sets/sci-fi-world-colony-ambience\" rel=\"nofollow\">Audio Demos</a></p><p><a href=\"https://www.youtube.com/watch?v&#61;UO-VMS-T7wk\" rel=\"nofollow\">Video Demos</a></p><p>This loop library includes over 119 location specific ambiance loops and loop-able layers which gives you the ability to accent your ambiances with sounds like air burst, air leak, wind and more.</p><p>Sci-fi World Colony includes 1.28 GB of samples to choose from and over 2 hours of loop-able background room tones and ambiances. Each loop is 1 minute in length and includes 1-2 alt versions per main loop. This allows you to orchestrate your game&#39;s background sound how you want it. If the full loop has too much going on, then try using the minimal version without the sound you don’t like.</p><p>Sci-fi World Colony is rapidly being added into sound designers banks as a reliable source of audio inspiration. You get to invent new worlds with immersive atmospheres and construct your background sound how you want it. Explore the depths of a mine or experience the sound of a sub bay with these scene setting tones.</p><p>Sci-fi World Colony is the first installment of the Sci-fi World ambiance loop library series. All of the recordings are royalty free and delivered in 44.1k 16bit .wav files, giving you the best quality for heavy sound editing, pitch shifting, and fx processing while keeping a top notch level of clarity and precision. Need more ambience loops? Be sure to check out Swarms sisters sound libraries - <a href=\"https://www.unrealengine.com/marketplace/sci-fi-world-swarm\" rel=\"nofollow\">Sci-fi World Swarm</a> and Sci-fi World Guardians.</p>",
  "technicalDetails": "<p>Features:</p><ul><li>119 game ready loop-able assets</li><li>1.28 GB of ambience samples</li><li>All in 44.1k 16bit .wav</li><li>Includes a 44.1k 16bit .wav version of library</li><li>Sci-fi Ambience Loop Library</li><li>Over 2 hours of sound</li><li>Includes a variety of locations</li><li>Perfect for games, room tones, and film</li><li>Includes embed Soundminer metadata</li><li>26 ambiences loops like an alien cave, energy lab, hangar, sub bay &amp; more</li><li>45 minimal version loops</li><li>48 loop-able layer loops like bio lab, air bursts, wind, air leak</li><li>All royalty free</li><li>RTU-OTB (ready to use out of the box)</li></ul><p>Number of Audio Waves: 119</p><p>Number of Audio Cues: 119</p><p>Sample rate / bit rate: 44.1 kHz, 16bit Stereo WAVs</p><p>Do Sound FX loop: Yes</p><p>Minutes of audio provided: 120 minutes</p><p>Supported Development Platforms: Windows, Mac, PS4, iOS, Android, Xbox One, Oculus, SteamVR / HTC Vive, Gear VR, Linux, HTML5</p><p>Supported Target Build Platforms: Windows, Mac, PS4, iOS, Android, Xbox One, Oculus, SteamVR / HTC Vive, Gear VR, Linux, HTML5</p><p>Documentation: <a href=\"https://epicstockmedia.com/wp-content/uploads/2018/08/Sci-fi_World_Colony.pdf\" rel=\"nofollow\">Content List</a></p>",
  "keyImages": [
    {
      "type": "Screenshot",
      "url": "https://cdn1.epicgames.com/ue/product/Screenshot/Sci-Fi World Colony-1080-1920x1080-f32a394fcf30d38ecb3dc4b46148cc6b.png",
      "md5": "f32a394fcf30d38ecb3dc4b46148cc6b",
      "width": 1920,
      "height": 1080,
      "size": 2335113,
      "uploadedDate": "2018-08-09T21:18:37.200Z"
    },
    {
      "type": "Screenshot",
      "url": "https://cdn1.epicgames.com/ue/product/Screenshot/screen-1-1920x1080-2db9e2968bc4fe434b98fb861b496c48.png",
      "md5": "2db9e2968bc4fe434b98fb861b496c48",
      "width": 1920,
      "height": 1080,
      "size": 556321,
      "uploadedDate": "2018-08-15T04:09:38.450Z"
    },
    {
      "type": "Screenshot",
      "url": "https://cdn1.epicgames.com/ue/product/Screenshot/screen-2-1920x1080-d5dabd3acf16a03c3849696250c0ae43.png",
      "md5": "d5dabd3acf16a03c3849696250c0ae43",
      "width": 1920,
      "height": 1080,
      "size": 543364,
      "uploadedDate": "2018-08-15T04:09:38.860Z"
    },
    {
      "type": "Screenshot",
      "url": "https://cdn1.epicgames.com/ue/product/Screenshot/screen-3-1920x1080-f1ecca8349e9f47043bad402b4b17f63.png",
      "md5": "f1ecca8349e9f47043bad402b4b17f63",
      "width": 1920,
      "height": 1080,
      "size": 1166588,
      "uploadedDate": "2018-08-15T04:09:39.318Z"
    },
    {
      "type": "Thumbnail",
      "url": "https://cdn1.epicgames.com/ue/product/Thumbnail/SciFiWorldColony_thumb-284x284-08c2d4c5085cd32d4d5d0c9df096d753.png",
      "md5": "08c2d4c5085cd32d4d5d0c9df096d753",
      "width": 284,
      "height": 284,
      "size": 171636,
      "uploadedDate": "2018-08-09T21:18:37.887Z"
    },
    {
      "type": "Featured",
      "url": "https://cdn1.epicgames.com/ue/product/Featured/SciFiWorldColony_featured-894x488-faf3d87c4cbb7134d8c7f38be8a89a2f.png",
      "md5": "faf3d87c4cbb7134d8c7f38be8a89a2f",
      "width": 894,
      "height": 488,
      "size": 674598,
      "uploadedDate": "2018-08-09T21:18:37.966Z"
    },
    {
      "type": "Snapshot",
      "url": "https://cdn1.epicgames.com/ue/product/Snapshot/screen-1-1920x1080-2db9e2968bc4fe434b98fb861b496c48_Snapshot.png",
      "md5": "95d516a55bb61d9ca08469a52e58a645",
      "width": 150,
      "height": 74,
      "size": 6873,
      "uploadedDate": "2018-08-15T04:09:38.690Z"
    },
    {
      "type": "Snapshot",
      "url": "https://cdn1.epicgames.com/ue/product/Snapshot/screen-2-1920x1080-d5dabd3acf16a03c3849696250c0ae43_Snapshot.png",
      "md5": "d547681f16c5c792ea4d5fdac23c5de4",
      "width": 150,
      "height": 74,
      "size": 6566,
      "uploadedDate": "2018-08-15T04:09:39.098Z"
    },
    {
      "type": "Snapshot",
      "url": "https://cdn1.epicgames.com/ue/product/Snapshot/screen-3-1920x1080-f1ecca8349e9f47043bad402b4b17f63_Snapshot.png",
      "md5": "e66672dc1c587e61241d4a32009dedd0",
      "width": 150,
      "height": 74,
      "size": 11499,
      "uploadedDate": "2018-08-15T04:09:39.677Z"
    },
    {
      "type": "Snapshot",
      "url": "https://cdn1.epicgames.com/ue/product/Snapshot/Sci-Fi World Colony-1080-1920x1080-f32a394fcf30d38ecb3dc4b46148cc6b_Snapshot.png",
      "md5": "aec81c5471466b0e07393789bf5e92d1",
      "width": 150,
      "height": 74,
      "size": 35448,
      "uploadedDate": "2018-08-09T21:18:37.769Z"
    }
  ],
  "categories": [
    {
      "path": "assets"
    },
    {
      "path": "assets/soundfx"
    }
  ],
  "namespace": "ue",
  "status": "ACTIVE",
  "creationDate": "2018-08-21T17:52:37.962Z",
  "lastModifiedDate": "2024-09-26T16:07:31.104Z",
  "customAttributes": {},
  "entitlementName": "b6c08618a4514f0a9f89819e7d8edd50",
  "entitlementType": "EXECUTABLE",
  "itemType": "DURABLE",
  "releaseInfo": [
    {
      "id": "085b13ab891c453a89c48a453d38a023",
      "appId": "SciFiWorb6c08618a451V1",
      "compatibleApps": [
        "UE_4.15",
        "UE_4.16",
        "UE_4.17",
        "UE_4.18",
        "UE_4.19",
        "UE_4.20",
        "UE_4.21",
        "UE_4.22",
        "UE_4.23",
        "UE_4.24",
        "UE_4.25",
        "UE_4.26",
        "UE_4.27",
        "UE_5.0",
        "UE_5.1",
        "UE_5.2",
        "UE_5.3",
        "UE_5.4"
      ],
      "platform": [
        "Linux",
        "Gear VR",
        "HTML5",
        "SteamVR / HTC Vive",
        "Oculus",
        "Xbox One",
        "Android",
        "iOS",
        "PS4",
        "Mac",
        "Windows",
        "Win32"
      ],
      "dateAdded": "2018-08-09T00:00:00.000Z",
      "releaseNote": "1.0",
      "versionTitle": "Sci-Fi World Colony "
    }
  ],
  "developer": "ESM Team",
  "developerId": "o-fb44d4d9ea4694aff4c7a497ccdb2e",
  "endOfSupport": false,
  "unsearchable": false
}