{
  "id": "f773be073c824fb8904da90fd4be022f",
  "title": "Anime Character Creator",
  "description": "A Character creator template for anime style. Able to add your custom content (hair, armor, eye, etc.)",
  "longDescription": "<p><strong>Proof/Making of :</strong></p><p><a href=\"https://www.youtube.com/watch?v&#61;HVWLXrrBssg&amp;list&#61;PLMZItZEyl7QIMmS6qc-rkXT2ijjpdRANe\" rel=\"nofollow\">Playlist Youtube Video</a></p><p><br /></p><p><strong>Docs</strong></p><p><a href=\"http://www.somndus-studio.com/en/assets-docs/anime-character-creator/\" rel=\"nofollow\">Documentation</a></p><p><a href=\"http://www.somndus-studio.com/en/assets-docs/anime-character-creator/acc-release-notes/acc-20-release-notes/\" rel=\"nofollow\">Last Release Note</a></p><p><br /></p><p><strong>Other videos: </strong></p><p><a href=\"https://www.youtube.com/playlist?list&#61;PLMZItZEyl7QIMmS6qc-rkXT2ijjpdRANe\" rel=\"nofollow\">Tutorial/Overview youtube playlist</a></p><p><br /></p><p><strong>Social :</strong></p><p><a href=\"https://discord.gg/2yWxCmA\" rel=\"nofollow\">Discord</a></p><p><br /></p><p><strong>Main Features :</strong></p><p>In Anime Character Creator Template you can customize your anim character and generate random characters from spawn points. This asset includes:</p><ul><li>Specie system (to manage different Skeleton version for example)</li><li>Maturity and Gender (Adult only in this template example)</li><li>Hair Edition</li><li>Eye customization : Iris color, style and size - Eye style - Eye brow style</li><li>Body morphology (Muscle, Fat or Slim) for each Gender (only for 1.5 Specie)</li><li>Equipement system (all equipped item will be registered in skinnable mesh array to fit the character)</li></ul><p><br /></p><p><strong>Notes : <u>The asset are a template of anime creator, he does not do everything and requires skills to integrate it into his own project</u></strong></p><p><strong><u>IMPORTANT : </u></strong>Be careful, this asset used some Object-oriented programming principles. To understand and modify code logic, it&#39;s recommended to know them.</p><p>ACC 1.9 ARE ONLY AVAILABLE TO UE4 4.26 ! A WAY TO USE IN 4.25 IT&#39;S TO MIGRATE ALL ASSETS FROM 4.26 (UNFOUNDED RESULT).</p>",
  "technicalDetails": "<p><strong>Number of Blueprints:</strong> 95</p><p><strong>Structs:</strong> 45</p><p><strong>Enum:</strong> 5</p><p><strong>DataTable:</strong> 43</p><p><br /></p><p><strong>Input:</strong> Keyboard</p><p><strong>Network Replicated:</strong> Only the customized character data are replicated, not the ui creation process</p><p><strong>Supported Development Platforms:</strong></p><p>Windows: Yes</p><p>Mac: No</p><p><br /></p><p><strong>Changelog: </strong></p><ul><li>1.0 : First project version, include basic creator system</li><li>1.5 : Maturity (baby added) - Networking - UI and Blueprints improvements.</li><li>1.9 : Epic Skeleton version added with Specie System. Many blueprint revamp and quickfix.</li><li>1.99 : Before 2.0 and UE5. Kind of user feedback validation before tag as 2.0</li><li>2.0 : UE5 migration and clean code</li><li>2.1 : UE5.1 migration, clean code, Epic Female Christmas Outfit, Whole costume/hat feature example.</li></ul><p><br /></p><p><strong>Engine Version: </strong>For Unreal Engine version please use</p><ul><li>4.25 &#61;&gt; Last hotfix</li><li>4.26 &#61;&gt; Last hotfix</li><li>4.27 &#61;&gt; Last hotfix</li><li>5.0 &#61;&gt; 5.03 Hotfix</li></ul><p><strong>Documentation:</strong></p><ul><li><a href=\"http://www.somndus-studio.com/en/assets-docs/anime-character-creator/\" rel=\"nofollow\">Documentation</a></li></ul><p><br /></p><p><strong>Important/Additional Notes: </strong></p><ul><li><strong>ONLY THE CUSTOMIZED CHARACTER DATA ARE REPLICATED, NOT THE UI CREATION PROCESS.</strong></li><li><strong>DON&#39;T BUY THIS ASSET IF YOU DIDN&#39;T HAVE ORIENTED OBJECT PROGRAMMING AND ADVANCED BLUEPRINT KNOWLEDGE (ESPECIALLY IF YOU ATTEMPT TO UNDERTSAND/EDIT THE CORE SYSTEM)</strong></li></ul>",
  "keyImages": [
    {
      "type": "Screenshot",
      "url": "https://cdn1.epicgames.com/ue/product/Screenshot/screenshot7-1920x1080-933771c2c4c57d9d613bfbd4c1a4f985.png",
      "md5": "933771c2c4c57d9d613bfbd4c1a4f985",
      "width": 1920,
      "height": 1080,
      "size": 930014,
      "uploadedDate": "2020-09-07T11:38:51.957Z"
    },
    {
      "type": "Screenshot",
      "url": "https://cdn1.epicgames.com/ue/product/Screenshot/screenshot6-1920x1080-d2e8682eb21c6eb72675374e80bcdeda.png",
      "md5": "d2e8682eb21c6eb72675374e80bcdeda",
      "width": 1920,
      "height": 1080,
      "size": 1345354,
      "uploadedDate": "2020-09-07T11:38:52.514Z"
    },
    {
      "type": "Screenshot",
      "url": "https://cdn1.epicgames.com/ue/product/Screenshot/screenshot5-1920x1080-fae6a9f05e7452671f86b9c0866abd4a.png",
      "md5": "fae6a9f05e7452671f86b9c0866abd4a",
      "width": 1920,
      "height": 1080,
      "size": 839490,
      "uploadedDate": "2020-09-07T11:38:52.994Z"
    },
    {
      "type": "Screenshot",
      "url": "https://cdn1.epicgames.com/ue/product/Screenshot/screen0-1920x1080-742b8efa000d22f04bc3464255f2c1e2.png",
      "md5": "742b8efa000d22f04bc3464255f2c1e2",
      "width": 1920,
      "height": 1080,
      "size": 832368,
      "uploadedDate": "2021-03-27T16:38:28.448Z"
    },
    {
      "type": "Screenshot",
      "url": "https://cdn1.epicgames.com/ue/product/Screenshot/screen1-1920x1080-12e81e573da895d9560203b22e5a2d12.png",
      "md5": "12e81e573da895d9560203b22e5a2d12",
      "width": 1920,
      "height": 1080,
      "size": 1406798,
      "uploadedDate": "2021-03-27T16:38:28.985Z"
    },
    {
      "type": "Screenshot",
      "url": "https://cdn1.epicgames.com/ue/product/Screenshot/screen3-1920x1080-3721b3aa265ad24d97d46f769a98a11a.png",
      "md5": "3721b3aa265ad24d97d46f769a98a11a",
      "width": 1920,
      "height": 1080,
      "size": 1297470,
      "uploadedDate": "2021-03-27T16:38:30.105Z"
    },
    {
      "type": "Screenshot",
      "url": "https://cdn1.epicgames.com/ue/product/Screenshot/screen4-1920x1080-60bae1cb63d6550e1b57ad7c6d176549.png",
      "md5": "60bae1cb63d6550e1b57ad7c6d176549",
      "width": 1920,
      "height": 1080,
      "size": 1415094,
      "uploadedDate": "2021-03-27T16:38:30.662Z"
    },
    {
      "type": "Screenshot",
      "url": "https://cdn1.epicgames.com/ue/product/Screenshot/Screenshot2-1920x1080-da9c3fa33c90b2c90f9b5f0422157441.jpg",
      "md5": "da9c3fa33c90b2c90f9b5f0422157441",
      "width": 1920,
      "height": 1080,
      "size": 1189199,
      "uploadedDate": "2022-07-19T17:07:12.310Z"
    },
    {
      "type": "Screenshot",
      "url": "https://cdn1.epicgames.com/ue/product/Screenshot/Screenshot1-1920x1080-c2a2f958b634f2cf7e3bcee2a37387f0.jpg",
      "md5": "c2a2f958b634f2cf7e3bcee2a37387f0",
      "width": 1920,
      "height": 1080,
      "size": 1171602,
      "uploadedDate": "2022-07-19T17:07:13.470Z"
    },
    {
      "type": "Thumbnail",
      "url": "https://cdn1.epicgames.com/ue/product/Thumbnail/AnimeCharacterCreator_thumb-284x284-c205d8e83ae038d5d20dc10fd6330917.png",
      "md5": "c205d8e83ae038d5d20dc10fd6330917",
      "width": 284,
      "height": 284,
      "size": 101116,
      "uploadedDate": "2022-07-19T17:07:14.304Z"
    },
    {
      "type": "Featured",
      "url": "https://cdn1.epicgames.com/ue/product/Featured/AnimeCharacterCreator_featured-894x488-307d2bc9982292132cf0af08b4c3d498.png",
      "md5": "307d2bc9982292132cf0af08b4c3d498",
      "width": 894,
      "height": 488,
      "size": 512392,
      "uploadedDate": "2022-07-19T17:07:14.421Z"
    },
    {
      "type": "Snapshot",
      "url": "https://cdn1.epicgames.com/ue/product/Snapshot/Screenshot2-1920x1080-da9c3fa33c90b2c90f9b5f0422157441_Snapshot.jpg",
      "md5": "634c47f386e20c7b8dde4e104071cd66",
      "width": 150,
      "height": 74,
      "size": 5283,
      "uploadedDate": "2022-07-19T17:07:13.077Z"
    },
    {
      "type": "Snapshot",
      "url": "https://cdn1.epicgames.com/ue/product/Snapshot/Screenshot1-1920x1080-c2a2f958b634f2cf7e3bcee2a37387f0_Snapshot.jpg",
      "md5": "381fe33d88f77297914bb72c549d236a",
      "width": 150,
      "height": 74,
      "size": 5240,
      "uploadedDate": "2022-07-19T17:07:14.250Z"
    },
    {
      "type": "Snapshot",
      "url": "https://cdn1.epicgames.com/ue/product/Snapshot/screen0-1920x1080-742b8efa000d22f04bc3464255f2c1e2_Snapshot.png",
      "md5": "5ecc1177e62840f58c4e0b22f7d2e00d",
      "width": 150,
      "height": 74,
      "size": 6248,
      "uploadedDate": "2021-03-27T16:38:28.791Z"
    },
    {
      "type": "Snapshot",
      "url": "https://cdn1.epicgames.com/ue/product/Snapshot/screen1-1920x1080-12e81e573da895d9560203b22e5a2d12_Snapshot.png",
      "md5": "8219bde173559a500b19e2f939f5a0d8",
      "width": 150,
      "height": 74,
      "size": 7178,
      "uploadedDate": "2021-03-27T16:38:29.338Z"
    },
    {
      "type": "Snapshot",
      "url": "https://cdn1.epicgames.com/ue/product/Snapshot/screen2-1920x1080-9a2f4a2c9a2dabbd6167d110c00e75a1_Snapshot.png",
      "md5": "d1d381fc94362d2944b39e6661e00d40",
      "width": 150,
      "height": 74,
      "size": 5509,
      "uploadedDate": "2021-03-27T16:38:29.911Z"
    },
    {
      "type": "Snapshot",
      "url": "https://cdn1.epicgames.com/ue/product/Snapshot/screen3-1920x1080-3721b3aa265ad24d97d46f769a98a11a_Snapshot.png",
      "md5": "44f429a04de1bbb83e5299d75e97c7de",
      "width": 150,
      "height": 74,
      "size": 6121,
      "uploadedDate": "2021-03-27T16:38:30.457Z"
    },
    {
      "type": "Snapshot",
      "url": "https://cdn1.epicgames.com/ue/product/Snapshot/screen4-1920x1080-60bae1cb63d6550e1b57ad7c6d176549_Snapshot.png",
      "md5": "43834f43c16232b5e930279db62291bd",
      "width": 150,
      "height": 74,
      "size": 6209,
      "uploadedDate": "2021-03-27T16:38:31.020Z"
    },
    {
      "type": "Snapshot",
      "url": "https://cdn1.epicgames.com/ue/product/Snapshot/screenshot7-1920x1080-933771c2c4c57d9d613bfbd4c1a4f985_Snapshot.png",
      "md5": "27f815829b6a97024329ae1e19ebf363",
      "width": 150,
      "height": 74,
      "size": 5045,
      "uploadedDate": "2020-09-07T11:38:52.320Z"
    },
    {
      "type": "Snapshot",
      "url": "https://cdn1.epicgames.com/ue/product/Snapshot/screenshot6-1920x1080-d2e8682eb21c6eb72675374e80bcdeda_Snapshot.png",
      "md5": "a878746ed5edde12a8e230a7d8d740f3",
      "width": 150,
      "height": 74,
      "size": 5780,
      "uploadedDate": "2020-09-07T11:38:52.871Z"
    },
    {
      "type": "Snapshot",
      "url": "https://cdn1.epicgames.com/ue/product/Snapshot/screenshot5-1920x1080-fae6a9f05e7452671f86b9c0866abd4a_Snapshot.png",
      "md5": "d05664e23a8c36720f8399d02c6b7040",
      "width": 150,
      "height": 74,
      "size": 4869,
      "uploadedDate": "2020-09-07T11:38:53.327Z"
    },
    {
      "type": "Snapshot",
      "url": "https://cdn1.epicgames.com/ue/product/Snapshot/screenshot4-1920x1080-2e3adce009985494c1a16939766fafe0_Snapshot.png",
      "md5": "e225a109b7dd008aa98c90b81a6c8196",
      "width": 150,
      "height": 74,
      "size": 6273,
      "uploadedDate": "2020-09-07T11:38:53.912Z"
    },
    {
      "type": "Snapshot",
      "url": "https://cdn1.epicgames.com/ue/product/Snapshot/screenshot3-1920x1080-90f95ab9b4319695589fca29336c6339_Snapshot.png",
      "md5": "f47096552e4ce625706ce611e2e52e01",
      "width": 150,
      "height": 74,
      "size": 5432,
      "uploadedDate": "2020-09-07T11:38:54.436Z"
    },
    {
      "type": "Snapshot",
      "url": "https://cdn1.epicgames.com/ue/product/Snapshot/screenshot2-1920x1080-c632e4c67ad10210f7e5f691e1f11ae1_Snapshot.png",
      "md5": "3f8347dcdd6eabd740fd8e94865bfe99",
      "width": 150,
      "height": 74,
      "size": 4962,
      "uploadedDate": "2020-09-07T11:38:54.951Z"
    },
    {
      "type": "Snapshot",
      "url": "https://cdn1.epicgames.com/ue/product/Snapshot/screenshot1-1920x1080-cac55a158ae45f226d374ba6634d715b_Snapshot.png",
      "md5": "6f42d1ea9a8d1bb40c8e2a1b8c591ded",
      "width": 150,
      "height": 74,
      "size": 5021,
      "uploadedDate": "2020-09-07T11:38:55.463Z"
    },
    {
      "type": "Snapshot",
      "url": "https://cdn1.epicgames.com/ue/product/Snapshot/Screen8-1920x1080-ec80b0346c5691ac726d4a42beeb18f6_Snapshot.png",
      "md5": "40d4e4cfd6343c1dd9f93934b46779c3",
      "width": 150,
      "height": 74,
      "size": 6938,
      "uploadedDate": "2020-03-17T12:19:04.844Z"
    },
    {
      "type": "Snapshot",
      "url": "https://cdn1.epicgames.com/ue/product/Snapshot/Screen1-1920x1080-cbe32b758d655f60408f157f4990c26f_Snapshot.png",
      "md5": "933955860e00c2358911c18efd68bbf5",
      "width": 150,
      "height": 74,
      "size": 4568,
      "uploadedDate": "2020-03-17T12:19:05.512Z"
    },
    {
      "type": "Snapshot",
      "url": "https://cdn1.epicgames.com/ue/product/Snapshot/Screen3-1920x1080-6e75b77cfae44b8b1f5c195dbe70510b_Snapshot.png",
      "md5": "c9947b77326d9d8c0dceac354fb188b7",
      "width": 150,
      "height": 74,
      "size": 5691,
      "uploadedDate": "2020-03-17T12:19:06.249Z"
    },
    {
      "type": "Snapshot",
      "url": "https://cdn1.epicgames.com/ue/product/Snapshot/Screen4-1920x1080-44c39097e090dfa3ca083467dccee9f6_Snapshot.png",
      "md5": "e84bf6a981dabd7e3e9b4c506e0cbf6f",
      "width": 150,
      "height": 74,
      "size": 4045,
      "uploadedDate": "2020-03-17T12:19:06.991Z"
    },
    {
      "type": "Snapshot",
      "url": "https://cdn1.epicgames.com/ue/product/Snapshot/Screen5-1920x1080-849e272f196ebf5fe3a4d4ecf85b6ae2_Snapshot.png",
      "md5": "2db443d49438c4a118fc15602c7565d4",
      "width": 150,
      "height": 74,
      "size": 3452,
      "uploadedDate": "2020-03-17T12:19:07.473Z"
    },
    {
      "type": "Snapshot",
      "url": "https://cdn1.epicgames.com/ue/product/Snapshot/Screen6-1920x1080-b463c9b8571931c5a6ab144e7b063d7d_Snapshot.png",
      "md5": "4a81729cd5595bfed7f5af220772aa68",
      "width": 150,
      "height": 74,
      "size": 4968,
      "uploadedDate": "2020-03-17T12:19:07.992Z"
    },
    {
      "type": "Snapshot",
      "url": "https://cdn1.epicgames.com/ue/product/Snapshot/Screen7-1920x1080-8dac12ca40ce91a660cef9ae0ab58ac3_Snapshot.png",
      "md5": "14181cdc41b3c6ac3f7608b94ed09f9f",
      "width": 150,
      "height": 74,
      "size": 4770,
      "uploadedDate": "2020-03-17T12:19:08.611Z"
    },
    {
      "type": "Snapshot",
      "url": "https://cdn1.epicgames.com/ue/product/Snapshot/Screen2-1920x1080-4b2dfd1d06b1c0a4d49efc3c2c5e0310_Snapshot.png",
      "md5": "8f87b8e22645b18afef6d016fdd48f50",
      "width": 150,
      "height": 74,
      "size": 6913,
      "uploadedDate": "2020-03-17T12:19:09.520Z"
    },
    {
      "type": "Snapshot",
      "url": "https://cdn1.epicgames.com/ue/product/Snapshot/Screen1-1920x1080-6af29960a4d53709f2c7c16e39913199_Snapshot.png",
      "md5": "865d8c4e0650f9fe95be6ce7a24c4794",
      "width": 150,
      "height": 74,
      "size": 4009,
      "uploadedDate": "2020-02-19T22:14:13.498Z"
    },
    {
      "type": "Snapshot",
      "url": "https://cdn1.epicgames.com/ue/product/Snapshot/Screen3-1920x1080-13c53482ba04a903489c13d5fc42b12b_Snapshot.png",
      "md5": "d7d4185c22fe27c0066f5f1817b1f35a",
      "width": 150,
      "height": 74,
      "size": 7018,
      "uploadedDate": "2020-02-19T21:37:49.864Z"
    },
    {
      "type": "Snapshot",
      "url": "https://cdn1.epicgames.com/ue/product/Snapshot/Screen1-1920x1080-6af29960a4d53709f2c7c16e39913199_Snapshot.png",
      "md5": "865d8c4e0650f9fe95be6ce7a24c4794",
      "width": 150,
      "height": 74,
      "size": 4009,
      "uploadedDate": "2020-02-19T20:47:57.294Z"
    },
    {
      "type": "Snapshot",
      "url": "https://cdn1.epicgames.com/ue/product/Snapshot/Screen2-1920x1080-b8f29fc51d84498dd60b93d46597da82_Snapshot.png",
      "md5": "1a724f611b2d7580de33437ee8c5f55d",
      "width": 150,
      "height": 74,
      "size": 5064,
      "uploadedDate": "2020-02-19T20:47:57.842Z"
    },
    {
      "type": "Snapshot",
      "url": "https://cdn1.epicgames.com/ue/product/Snapshot/Screen3-1920x1080-13c53482ba04a903489c13d5fc42b12b_Snapshot.png",
      "md5": "d7d4185c22fe27c0066f5f1817b1f35a",
      "width": 150,
      "height": 74,
      "size": 7018,
      "uploadedDate": "2020-02-19T20:47:58.378Z"
    },
    {
      "type": "Snapshot",
      "url": "https://cdn1.epicgames.com/ue/product/Snapshot/Screen4-1920x1080-7b6b8e026b64c72ac6b7a5f62038910d_Snapshot.png",
      "md5": "b08ccf881a6bb26f792b1b9f3f6c486a",
      "width": 150,
      "height": 74,
      "size": 5182,
      "uploadedDate": "2020-02-19T20:47:59.112Z"
    },
    {
      "type": "Snapshot",
      "url": "https://cdn1.epicgames.com/ue/product/Snapshot/Screen5-1920x1080-ce53af77b0b269e4400cc85076672749_Snapshot.png",
      "md5": "a797b5c89ac493f439dc21f36cd8140d",
      "width": 150,
      "height": 74,
      "size": 5594,
      "uploadedDate": "2020-02-19T20:47:59.640Z"
    },
    {
      "type": "Snapshot",
      "url": "https://cdn1.epicgames.com/ue/product/Snapshot/Screen6-1920x1080-24cd7727642b58ccb3ff097c03d8b487_Snapshot.png",
      "md5": "a3757e3cfa59a2a31281a906faa00a4b",
      "width": 150,
      "height": 74,
      "size": 3398,
      "uploadedDate": "2020-02-19T20:48:00.043Z"
    },
    {
      "type": "Snapshot",
      "url": "https://cdn1.epicgames.com/ue/product/Snapshot/Screen7-1920x1080-8563f66e1ae7a585487899ecb9567a88_Snapshot.png",
      "md5": "ed24200fd9ed830b5fcb02f0a3cd670e",
      "width": 150,
      "height": 74,
      "size": 4672,
      "uploadedDate": "2020-02-19T20:48:00.592Z"
    },
    {
      "type": "Snapshot",
      "url": "https://cdn1.epicgames.com/ue/product/Snapshot/Screen8-1920x1080-9f71a2908d3f5831f5134bcc67809078_Snapshot.png",
      "md5": "12a4f19ec1577061a45a9fefeed356a7",
      "width": 150,
      "height": 74,
      "size": 4367,
      "uploadedDate": "2020-02-19T20:48:01.206Z"
    },
    {
      "type": "Snapshot",
      "url": "https://cdn1.epicgames.com/ue/product/Snapshot/Screen9-1920x1080-0bbd7e171fdc208956d790da5d1ba380_Snapshot.png",
      "md5": "f9fee89f9d5b15b4970b0cc98ccdaeaa",
      "width": 150,
      "height": 74,
      "size": 4995,
      "uploadedDate": "2020-02-19T20:48:01.872Z"
    }
  ],
  "categories": [
    {
      "path": "projects"
    },
    {
      "path": "projects/completeprojects"
    }
  ],
  "namespace": "ue",
  "status": "SUNSET",
  "creationDate": "2020-03-23T18:23:04.182Z",
  "lastModifiedDate": "2023-09-11T17:54:23.837Z",
  "entitlementName": "f773be073c824fb8904da90fd4be022f",
  "entitlementType": "EXECUTABLE",
  "itemType": "DURABLE",
  "releaseInfo": [
    {
      "id": "7e110b35229248d9a49f582298f3ec74",
      "appId": "AnimeChaf773be073c82V1",
      "compatibleApps": [
        "UE_4.25"
      ],
      "platform": [
        "Windows",
        "Win32"
      ],
      "dateAdded": "2020-02-19T00:00:00.000Z",
      "releaseNote": "Maturity system, Network replication, UI and Blueprints improvement",
      "versionTitle": "Anime Character Creator - V1.5"
    },
    {
      "id": "fb792d579f6e4013946125e77cb95e45",
      "appId": "AnimeChaf773be073c82V3",
      "compatibleApps": [
        "UE_4.26"
      ],
      "platform": [
        "Windows",
        "Win32"
      ],
      "dateAdded": "2021-03-22T00:00:00.000Z",
      "releaseNote": "Version 1.9 with Epic Skeleton example.",
      "versionTitle": "Anime Character Creator - V1.9"
    },
    {
      "id": "9deea0ee2deb4cebaa8461acea212c2f",
      "appId": "AnimeChaf773be073c82V4",
      "compatibleApps": [
        "UE_4.27"
      ],
      "platform": [
        "Win32",
        "Windows"
      ],
      "dateAdded": "2021-10-20T00:00:00.000Z",
      "releaseNote": "1.9.9 - Clean and improve before 2.0 and ue5",
      "versionTitle": "ACC - V1.9.9 - UE4.27.3"
    },
    {
      "id": "1019de5bae9842af8b9dc755f24e3484",
      "appId": "AnimeChaf773be073c82V5",
      "compatibleApps": [
        "UE_5.0"
      ],
      "platform": [
        "Windows"
      ],
      "dateAdded": "2022-07-18T00:00:00.000Z",
      "releaseNote": "Clean code and some new features to ue5.0.3",
      "versionTitle": "ACC - 2.0 - UE5.0.3"
    },
    {
      "id": "f43a90bd7032490e88ee5540c3055bcf",
      "appId": "AnimeChaf773be073c82V6",
      "compatibleApps": [
        "UE_5.1"
      ],
      "platform": [
        "Windows"
      ],
      "dateAdded": "2023-01-08T00:00:00.000Z",
      "releaseNote": "UE5.1 Migration + 5.0.3 update",
      "versionTitle": "ACC - 2.0 - UE5.1"
    },
    {
      "id": "4d52f0c401264f0da8a2f51deca24aed",
      "appId": "AnimeChaf773be073c82V7",
      "compatibleApps": [
        "UE_5.2"
      ],
      "platform": [
        "Windows"
      ],
      "dateAdded": "2023-06-05T00:00:00.000Z",
      "releaseNote": "",
      "versionTitle": "ACC - UE5.2"
    }
  ],
  "developer": "Somndus Studio",
  "developerId": "o-kjpv7eqn2mhely7pm5lj7mclb9l6k2",
  "endOfSupport": false,
  "unsearchable": false
}